poetaster/__init__.py
poetaster/__main__.py
poetaster/cli.py
poetaster/haiku.py
poetaster/lattice.py
poetaster-0.1.1.dist-info/DESCRIPTION.rst
poetaster-0.1.1.dist-info/METADATA
poetaster-0.1.1.dist-info/RECORD
poetaster-0.1.1.dist-info/WHEEL
poetaster-0.1.1.dist-info/entry_points.txt
poetaster-0.1.1.dist-info/metadata.json
poetaster-0.1.1.dist-info/top_level.txt
