Metadata-Version: 2.0
Name: poetaster
Version: 0.1.1
Summary: Poetry tricks and tools for found -- and generated -- poetry.
Home-page: https://github.com/jkahn/python-poetaster
Author: Jeremy G. Kahn
Author-email: jeremy@trochee.net
License: BSD
Keywords: poetry,metric analysis,silly lexical tricks
Platform: UNKNOWN
Classifier: Development Status :: 1 - Planning
Classifier: Intended Audience :: Developers
Classifier: License :: OSI Approved :: BSD License
Classifier: Operating System :: Unix
Classifier: Operating System :: POSIX
Classifier: Operating System :: Microsoft :: Windows
Classifier: Programming Language :: Python
Classifier: Programming Language :: Python :: 2.7
Classifier: Programming Language :: Python :: 3
Classifier: Programming Language :: Python :: 3.4
Classifier: Programming Language :: Python :: 3.5
Classifier: Programming Language :: Python :: Implementation :: CPython
Classifier: Programming Language :: Python :: Implementation :: PyPy
Classifier: Topic :: Utilities
Requires-Dist: click
Requires-Dist: islex (>=0.2.2)
Requires-Dist: islex-core
Requires-Dist: islex-entities
